vietnamese_conceptizer/__init__.py
vietnamese_conceptizer/processor.py
vietnamese_conceptizer-0.1.2.dist-info/METADATA
vietnamese_conceptizer-0.1.2.dist-info/WHEEL
vietnamese_conceptizer-0.1.2.dist-info/top_level.txt
vietnamese_conceptizer-0.1.2.dist-info/RECORD
