Metadata-Version: 2.2
Name: vietnamese_conceptizer
Version: 0.1.2
Summary: A tool for processing text files and normalizing data using a dictionary
Home-page: https://github.com/luongducthangDS/vietnamese_conceptizer
Author: Bui Van Tan; Luong Duc Thang
Author-email: luongducthang289@gmail.com
License: MIT
Classifier: Programming Language :: Python :: 3
Classifier: License :: OSI Approved :: MIT License
Classifier: Operating System :: OS Independent
Requires-Python: >=3.7
Requires-Dist: pandas
Dynamic: author
Dynamic: author-email
Dynamic: classifier
Dynamic: description
Dynamic: description-content-type
Dynamic: home-page
Dynamic: license
Dynamic: requires-dist
Dynamic: requires-python
Dynamic: summary
